zoom_dl/__init__.py
zoom_dl/__main__.py
zoom_dl/cookiejar.py
zoom_dl/parser.py
zoom_dl/version.py
zoom_dl/zoomdl.py
zoomdl_2-1970.1.1.dist-info/LICENSE
zoomdl_2-1970.1.1.dist-info/METADATA
zoomdl_2-1970.1.1.dist-info/WHEEL
zoomdl_2-1970.1.1.dist-info/top_level.txt
zoomdl_2-1970.1.1.dist-info/RECORD
