Metadata-Version: 2.1
Name: zoomdl-2
Version: 1970.1.1
Summary: Download Zoom recorded meetings easily
Home-page: https://github.com/battleman/zoomdl
Author: Olivier Cloux
Author-email: zoomdl@cloux.dev
License: UNKNOWN
Project-URL: Bug Tracker, https://github.com/battleman/zoomdl/issues
Platform: UNKNOWN
Classifier: Programming Language :: Python :: 3
Classifier: License :: OSI Approved :: GNU General Public License v3 (GPLv3)
Classifier: Operating System :: OS Independent
Requires-Python: >=3.6
License-File: LICENSE
Requires-Dist: requests
Requires-Dist: demjson
Requires-Dist: tqdm
